mac_imessage/__init__.py
mac_imessage/__main__.py
mac_imessage/custom_types.py
mac_imessage/exceptions.py
mac_imessage/utils.py
mac_imessage-0.3.0.dist-info/LICENSE
mac_imessage-0.3.0.dist-info/METADATA
mac_imessage-0.3.0.dist-info/WHEEL
mac_imessage-0.3.0.dist-info/top_level.txt
mac_imessage-0.3.0.dist-info/RECORD
