Metadata-Version: 2.1
Name: mac_imessage
Version: 0.3.0
Summary: Python tools for sending iMessages / SMS on a Mac
Home-page: https://pypi.org/project/mac_imessage/
Author: James Kabbes
Author-email: james.kabbes@gmail.com
Project-URL: GitHub, https://github.com/jameskabbes/imessage
Project-URL: Documentation, https://jameskabbes.github.io/imessage
Classifier: Programming Language :: Python :: 3
Classifier: License :: OSI Approved :: MIT License
Classifier: Operating System :: OS Independent
Requires-Python: >=3.12
License-File: LICENSE
